llama_index/readers/kaltura_esearch/__init__.py
llama_index/readers/kaltura_esearch/base.py
llama_index_readers_kaltura_esearch-0.4.1.dist-info/METADATA
llama_index_readers_kaltura_esearch-0.4.1.dist-info/WHEEL
llama_index_readers_kaltura_esearch-0.4.1.dist-info/licenses/LICENSE
llama_index_readers_kaltura_esearch-0.4.1.dist-info/RECORD
