Metadata-Version: 2.4
Name: llama-index-readers-kaltura-esearch
Version: 0.4.1
Summary: llama-index readers kaltura e-search integration
Author-email: Your Name <you@example.com>
Maintainer: kaltura
License-Expression: AGPL-3.0
License-File: LICENSE
Keywords: audio,events,image,kaltura,library,media,portal,search,video
Requires-Python: <4.0,>=3.9
Requires-Dist: kalturaapiclient<19.4.0,>=19.3.0
Requires-Dist: llama-index-core<0.15,>=0.13.0
